box_tools_ai.py
box_tools_docgen.py
box_tools_files.py
box_tools_folders.py
box_tools_generic.py
box_tools_metadata.py
box_tools_search.py
mcp_server_box.py
server_context.py
mseep_mcp_server_box-0.1.4.dist-info/METADATA
mseep_mcp_server_box-0.1.4.dist-info/WHEEL
mseep_mcp_server_box-0.1.4.dist-info/top_level.txt
mseep_mcp_server_box-0.1.4.dist-info/RECORD
