Metadata-Version: 2.4
Name: mseep-mcp-server-box
Version: 0.1.4
Summary: Add your description here
Author-email: mseep <support@skydeck.ai>
Requires-Python: >=3.13
Requires-Dist: box-ai-agents-toolkit>=0.0.44
Requires-Dist: fastapi>=0.115.14
Requires-Dist: mcp[cli]>=1.10.1
Requires-Dist: python-dotenv>=1.1.1
